nekoai/__init__.py
nekoai/__main__.py
nekoai/_version.py
nekoai/client.py
nekoai/constant.py
nekoai/exceptions.py
nekoai/utils.py
nekoai/types/__init__.py
nekoai/types/constant.py
nekoai/types/director.py
nekoai/types/image.py
nekoai/types/metadata.py
nekoai/types/parameters.py
nekoai/types/user.py
nekoai_api-0.3.1.dist-info/licenses/LICENSE
nekoai_api-0.3.1.dist-info/METADATA
nekoai_api-0.3.1.dist-info/WHEEL
nekoai_api-0.3.1.dist-info/entry_points.txt
nekoai_api-0.3.1.dist-info/top_level.txt
nekoai_api-0.3.1.dist-info/RECORD
