Metadata-Version: 2.4
Name: nekoai-api
Version: 0.3.1
Summary: 🎨 A lightweight async Python API for NovelAI image generation and director tools.
Author-email: "Nya Foundation Team (k3scat)" <k3scat@gmail.com>
License-Expression: AGPL-3.0
Project-URL: Repository, https://github.com/Nya-Foundation/NekoAI-API
Project-URL: Issues, https://github.com/Nya-Foundation/NekoAI-API/issues
Keywords: API,async,NovelAI,AI,image generation,nai3,nai4
Classifier: Development Status :: 4 - Beta
Classifier: Intended Audience :: Developers
Classifier: Programming Language :: Python :: 3
Classifier: Programming Language :: Python :: 3.10
Classifier: Programming Language :: Python :: 3.11
Classifier: Programming Language :: Python :: 3.12
Classifier: Programming Language :: Python :: 3.13
Requires-Python: >=3.10
License-File: LICENSE
Requires-Dist: httpx>=0.25.2
Requires-Dist: pydantic>=2.5.3
Requires-Dist: loguru>=0.7.2
Requires-Dist: argon2-cffi>=21.3.0
Requires-Dist: msgpack>=1.1.0
Dynamic: license-file
